{
  "hash": "71e5e2e0",
  "configHash": "a6415141",
  "lockfileHash": "0899f609",
  "browserHash": "24fb619f",
  "optimized": {
    "vue": {
      "src": "../../../../node_modules/vue/dist/vue.runtime.esm-bundler.js",
      "file": "vue.js",
      "fileHash": "9950329d",
      "needsInterop": false
    },
    "vitepress > @vue/devtools-api": {
      "src": "../../../../node_modules/@vue/devtools-api/dist/index.js",
      "file": "vitepress___@vue_devtools-api.js",
      "fileHash": "20cb44fa",
      "needsInterop": false
    },
    "vitepress > @vueuse/core": {
      "src": "../../../../node_modules/vitepress/node_modules/@vueuse/core/index.mjs",
      "file": "vitepress___@vueuse_core.js",
      "fileHash": "efdaf88a",
      "needsInterop": false
    },
    "vitepress-plugin-blog": {
      "src": "../../../../node_modules/vitepress-plugin-blog/dist/index.js",
      "file": "vitepress-plugin-blog.js",
      "fileHash": "f9d7d73c",
      "needsInterop": false
    }
  },
  "chunks": {
    "BlogFilters.vue-IQYCIA6D": {
      "file": "BlogFilters__vue-IQYCIA6D.js"
    },
    "BlogPagination.vue-T3QKXGQE": {
      "file": "BlogPagination__vue-T3QKXGQE.js"
    },
    "useBlogNavigation-6RYLFY6E": {
      "file": "useBlogNavigation-6RYLFY6E.js"
    },
    "BlogPostLayout.vue-KYMF7G7S": {
      "file": "BlogPostLayout__vue-KYMF7G7S.js"
    },
    "BlogLayoutWrapper.vue-43D7G3CB": {
      "file": "BlogLayoutWrapper__vue-43D7G3CB.js"
    },
    "chunk-2MIMKAAD": {
      "file": "chunk-2MIMKAAD.js"
    },
    "BlogIndex.vue-SVSEO4NZ": {
      "file": "BlogIndex__vue-SVSEO4NZ.js"
    },
    "chunk-IMJ32XNN": {
      "file": "chunk-IMJ32XNN.js"
    },
    "chunk-GV7W5DTG": {
      "file": "chunk-GV7W5DTG.js"
    },
    "chunk-322YQTTG": {
      "file": "chunk-322YQTTG.js"
    },
    "BlogCard.vue-MMGOGPJN": {
      "file": "BlogCard__vue-MMGOGPJN.js"
    },
    "chunk-J4Q5XZY7": {
      "file": "chunk-J4Q5XZY7.js"
    },
    "chunk-MXGY3IJX": {
      "file": "chunk-MXGY3IJX.js"
    },
    "chunk-HCPEYRNK": {
      "file": "chunk-HCPEYRNK.js"
    },
    "chunk-NPGVKGNX": {
      "file": "chunk-NPGVKGNX.js"
    },
    "chunk-7D4SUZUM": {
      "file": "chunk-7D4SUZUM.js"
    }
  }
}